bruhh/cli/main.py
bruhh/cli/subcommands/__init__.py
bruhh/cli/subcommands/system.py
bruhh/cli/system/service-requirements.txt
bruhh/daemon/main.py
bruhh-0.1.1.dist-info/LICENSE
bruhh-0.1.1.dist-info/METADATA
bruhh-0.1.1.dist-info/WHEEL
bruhh-0.1.1.dist-info/entry_points.txt
bruhh-0.1.1.dist-info/RECORD
